{
  "tut-occupancy" : {
    "/webcomponents-lite.min.js" : {
      "version" : "0.0.93",
      "lastModified" : 1548956740932,
      "metaId" : 14912449,
      "fileId" : "(dev=1000004,ino=9798090)"
    },
    "/esri_placeholder.png" : {
      "version" : "0.0.70",
      "lastModified" : 1548964631556,
      "metaId" : 14912806,
      "fileId" : "(dev=1000004,ino=9854817)"
    },
    "/leaflet.css" : {
      "version" : "0.0.104",
      "lastModified" : 499162500000,
      "metaId" : 14912389,
      "fileId" : "(dev=1000004,ino=9797609)"
    },
    "/tut-occupancy-styles.html" : {
      "version" : "0.0.156",
      "lastModified" : 1548963298032,
      "metaId" : 14910927,
      "fileId" : "(dev=1000004,ino=9662207)"
    },
    "/leaflet-map.html" : {
      "version" : "0.0.98",
      "lastModified" : 1548956329832,
      "metaId" : 14912415,
      "fileId" : "(dev=1000004,ino=9797983)"
    },
    "/leaflet-marker.html" : {
      "version" : "0.0.96",
      "lastModified" : 1548956416580,
      "metaId" : 14912430,
      "fileId" : "(dev=1000004,ino=9798000)"
    },
    "/tut-occupancy.html" : {
      "version" : "0.0.353",
      "lastModified" : 1549646345304,
      "metaId" : 14910869,
      "fileId" : "(dev=1000004,ino=9662208)"
    },
    "/leaflet.js" : {
      "version" : "0.0.105",
      "lastModified" : 499162500000,
      "metaId" : 14912384,
      "fileId" : "(dev=1000004,ino=9797610)"
    }
  }
}